Metadata-Version: 1.0
Name: SPrompt
Version: 0.0.1b1
Summary: ChokChaisak
Home-page: https://github.com/ChokChaisak/ChokChaisak
Author: ChokChaisak
Author-email: ChokChaisak@gmail.com
License: ChokChaisak
Keywords: SPrompt
Platform: UNKNOWN
